README.md
setup.py
repsimtools/__init__.py
repsimtools/dumbparallel.py
repsimtools/tools.py
repsimtools.egg-info/PKG-INFO
repsimtools.egg-info/SOURCES.txt
repsimtools.egg-info/dependency_links.txt
repsimtools.egg-info/requires.txt
repsimtools.egg-info/top_level.txt