Metadata-Version: 2.1
Name: repsimtools
Version: 0.0.1
Summary: Tools for parallel simulation with git source control.
Home-page: https://github.com/fakufaku/repsimtools
Author: Robin Scheibler
Author-email: fakufaku@gmail.com
License: UNKNOWN
Platform: UNKNOWN
Classifier: Programming Language :: Python :: 3
Classifier: License :: OSI Approved :: MIT License
Classifier: Operating System :: OS Independent
Requires-Python: >=3.6
